CODEOWNERS
LICENSE
MANIFEST.in
README.md
setup.py
Metis/__init__.py
Metis/tools/HDF5Helper.py
Metis/tools/STDFHelper.py
Metis/tools/__init__.py
Metis/tools/stdf2csv.py
Metis/tools/stdf2ph5.py
Semi_ATE_Metis.egg-info/PKG-INFO
Semi_ATE_Metis.egg-info/SOURCES.txt
Semi_ATE_Metis.egg-info/dependency_links.txt
Semi_ATE_Metis.egg-info/top_level.txt
documentation/METIS.pptm
documentation/STDF_to_Pandas.xlsx
documentation/reports/A4.png
documentation/reports/Capture.PNG
documentation/reports/Lot-Test-Summary.png
documentation/reports/LotTest.png
documentation/reports/ProbingSummaryPage.png
documentation/reports/ProbingTop.xcf
documentation/reports/ProbingTopBackground.png
documentation/reports/ProbingTopTestPerLot.png
documentation/reports/ProbingTopTestPerWafer.png
documentation/reports/ProbingTopTestsPerWafer.png
documentation/reports/README.md
documentation/reports/SummaryPage.pdf
documentation/reports/SummaryPage.png
documentation/reports/SummaryPageLotWafer.png
documentation/reports/TestPerLot.png
documentation/reports/TestPerWafer.png
documentation/reports/TestResultPage.pdf
documentation/reports/TestResultPage.png
documentation/reports/autoreports.pptx
documentation/reports/home.png
documentation/reports/lot-wafer.png
documentation/reports/tables.xlsx
requirements/run.txt
requirements/test.txt